cfdns/__init__.py
cfdns/cf_dns.py
getmyip/__init__.py
getmyip/getmyip.py
setmycfdns/__init__.py
setmycfdns/set_my_cf_dns.py
setmycfdns-24.12.25.data/scripts/setmycfdns
setmycfdns-24.12.25.dist-info/LICENSE.txt
setmycfdns-24.12.25.dist-info/METADATA
setmycfdns-24.12.25.dist-info/WHEEL
setmycfdns-24.12.25.dist-info/top_level.txt
setmycfdns-24.12.25.dist-info/RECORD
