Metadata-Version: 2.1
Name: setmycfdns
Version: 24.12.25
Summary: Updates a hosts cloudflare record
Home-page: https://github.com/Glocktober/setmycfdns
Author: gunville
Author-email: rk13088@yahoo.com
Project-URL: repo, https://github.com/Glocktober/setmycfdns.git
Project-URL: overview, https://github.com/Glocktober/setmycfdns/blob/master/README.md
Keywords: 'cloudflare cloud dns'
Classifier: Programming Language :: Python :: 3
Classifier: License :: OSI Approved :: MIT License
Classifier: Operating System :: OS Independent
Requires-Python: >=3.6
License-File: LICENSE.txt
Requires-Dist: cloudflare>=3.1.1
Requires-Dist: Requests>=2.32.0
